[{"imdb_id": "nm0841552", "name": " Arvind Swamy\n"}, {"imdb_id": "nm0463539", "name": " Manisha Koirala\n"}, {"imdb_id": "nm0621937", "name": " Nassar\n"}, {"imdb_id": "nm1390149", "name": " Kitty\n"}, {"imdb_id": "nm1218624", "name": " Master Harsha\n"}, {"imdb_id": "nm1389854", "name": " Master Hriday\n"}, {"imdb_id": "nm0025627", "name": " Tinnu Anand\n"}, {"imdb_id": "nm0452021", "name": " Akash Khurana\n"}, {"imdb_id": "nm1377248", "name": " Nagendra Prasad\n"}, {"imdb_id": "nm0695177", "name": " Prakash Raj\n"}, {"imdb_id": "nm0007114", "name": " Sonali Bendre\n"}, {"imdb_id": "nm1115041", "name": " M.V. Vasudeva Rao\n"}, {"imdb_id": "nm1391274", "name": " Ratnakar\n"}, {"imdb_id": "nm0707723", "name": " Rallapalli\n"}, {"imdb_id": "nm1390550", "name": " Deesh Mariwala\n"}]