[{"imdb_id": "nm2601111", "name": " Nazriya Nazim\n"}, {"imdb_id": "nm4028885", "name": " Nivin Pauly\n"}, {"imdb_id": "nm4921260", "name": " Dulquer Salmaan\n"}, {"imdb_id": "nm1335704", "name": " Fahadh Faasil\n"}, {"imdb_id": "nm2527173", "name": " Parvathy Thiruvothu\n"}, {"imdb_id": "nm1589340", "name": " Isha Talwar\n"}, {"imdb_id": "nm3383930", "name": " Nithya Menon\n"}, {"imdb_id": "nm1427780", "name": " Kalpana\n"}, {"imdb_id": "nm0683477", "name": " Maniyanpilla Raju\n"}, {"imdb_id": "nm0695595", "name": " Praveena\n"}, {"imdb_id": "nm1066795", "name": " Vijayaraghavan\n"}, {"imdb_id": "nm7328054", "name": " Sijoy Varghese\n"}, {"imdb_id": "nm6325282", "name": " Sajid Yahiya\n"}, {"imdb_id": "nm0693092", "name": " Prathap Pothen\n"}, {"imdb_id": "nm1110573", "name": " Vinaya Prakash\n"}]